pythonHtmlWeb/__init__.py
pythonHtmlWeb/htmlCode.py
pythonHtmlWeb-1.0.1.dist-info/LICENSE
pythonHtmlWeb-1.0.1.dist-info/METADATA
pythonHtmlWeb-1.0.1.dist-info/WHEEL
pythonHtmlWeb-1.0.1.dist-info/top_level.txt
pythonHtmlWeb-1.0.1.dist-info/RECORD
